sdkms_plugin_registry_builder/__init__.py
sdkms_plugin_registry_builder/__main__.py
sdkms_plugin_registry_builder-1.3.0.dist-info/METADATA
sdkms_plugin_registry_builder-1.3.0.dist-info/WHEEL
sdkms_plugin_registry_builder-1.3.0.dist-info/entry_points.txt
sdkms_plugin_registry_builder-1.3.0.dist-info/top_level.txt
sdkms_plugin_registry_builder-1.3.0.dist-info/RECORD
