Metadata-Version: 2.1
Name: sdkms-plugin-registry-builder
Version: 1.3.0
Summary: Fortanix DSM Plugin Registry Builder
Home-page: https://support.fortanix.com
Author: Fortanix
Author-email: support@fortanix.com
License: Apache 2.0
Keywords: SDKMS,DSM,Fortanix DSM,plugin-registry
Classifier: Development Status :: 5 - Production/Stable
Classifier: Intended Audience :: Developers
Classifier: Intended Audience :: System Administrators
Classifier: License :: OSI Approved :: Apache Software License
Classifier: Programming Language :: Python :: 2
Classifier: Programming Language :: Python :: 3
Classifier: Topic :: Security :: Cryptography
Requires-Python: >=3.7
Requires-Dist: gitpython ~=3.1.44
